libcava/__init__.py
python_libcava-1.0.0.dist-info/licenses/LICENSE
python_libcava-1.0.0.dist-info/METADATA
python_libcava-1.0.0.dist-info/WHEEL
python_libcava-1.0.0.dist-info/top_level.txt
python_libcava-1.0.0.dist-info/RECORD
