Metadata-Version: 2.4
Name: python-libcava
Version: 1.0.0
Summary: Python bindings for cava audio visualizer
Home-page: https://github.com/LIZARD-OFFICIAL-77/python-libcava/
Author: LIZARD-OFFICIAL-77
Author-email: <lizard.official.77@gmail.com>
License: 
Project-URL: Source Code, https://github.com/LIZARD-OFFICIAL-77/python-libcava/
Project-URL: Bug Tracker, https://github.com/LIZARD-OFFICIAL-77/python-libcava/issues
Keywords: open-source,foss,cava,linux,fifo
Classifier: Programming Language :: Python :: 3 :: Only
Classifier: Operating System :: POSIX :: Linux
License-File: LICENSE
Dynamic: author
Dynamic: author-email
Dynamic: classifier
Dynamic: description
Dynamic: description-content-type
Dynamic: home-page
Dynamic: keywords
Dynamic: license
Dynamic: license-file
Dynamic: project-url
Dynamic: summary
